{"data":{"_id":5000,"properties":{"post":{"name":"post","kind":"m:1","cascade":["persist"],"deleteRule":"cascade","primary":true,"owner":true,"createForeignKeyConstraint":true,"type":"BlogPosts","array":false,"runtimeType":"BlogPosts"},"tag":{"name":"tag","kind":"scalar","primary":true,"length":80,"getter":false,"setter":false,"type":"string","array":false,"runtimeType":"string"}},"primaryKeys":["post","tag"],"filters":{},"hooks":{},"indexes":[],"uniques":[],"className":"BlogTags","path":"./src/entities/BlogTags.ts","name":"BlogTags","abstract":false,"internal":true,"constructorParams":[],"toJsonParams":[],"useCache":true,"compositePK":true,"simplePK":false,"collection":"blog_tags"},"origin":"./src/entities/BlogTags.ts","hash":"557a187ce304219a8544af86b934d637","version":"6.6.9"}
